nlx_url_rewriter/__init__.py
nlx_url_rewriter/admin.py
nlx_url_rewriter/apps.py
nlx_url_rewriter/models.py
nlx_url_rewriter/rewriter.py
nlx_url_rewriter/migrations/0001_initial.py
nlx_url_rewriter/migrations/__init__.py
nlx_url_rewriter-0.1.2.dist-info/LICENSE
nlx_url_rewriter-0.1.2.dist-info/METADATA
nlx_url_rewriter-0.1.2.dist-info/WHEEL
nlx_url_rewriter-0.1.2.dist-info/top_level.txt
nlx_url_rewriter-0.1.2.dist-info/RECORD
