Metadata-Version: 2.1
Name: nlx-url-rewriter
Version: 0.1.2
Summary: Plumbing to rewrite URLs in forward and reverse direction
Home-page: https://github.com/maykinmedia/nlx-url-rewriter
Author: Maykin Media
Author-email: support@maykinmedia.nl
License: MIT
Keywords: requests,api,urls,rewrite,middleware
Platform: UNKNOWN
Classifier: Development Status :: 3 - Alpha
Classifier: Framework :: Django
Classifier: Framework :: Django :: 2.2
Classifier: Intended Audience :: Developers
Classifier: Operating System :: Unix
Classifier: Operating System :: MacOS
Classifier: Operating System :: Microsoft :: Windows
Classifier: Programming Language :: Python :: 3.7
Classifier: Topic :: Software Development :: Libraries :: Python Modules
Requires-Dist: django
Provides-Extra: coverage
Requires-Dist: pytest-cov ; extra == 'coverage'
Provides-Extra: docs
Requires-Dist: sphinx ; extra == 'docs'
Requires-Dist: sphinx-rtd-theme ; extra == 'docs'
Provides-Extra: release
Requires-Dist: bumpversion ; extra == 'release'
Requires-Dist: twine ; extra == 'release'
Provides-Extra: tests
Requires-Dist: pytest ; extra == 'tests'
Requires-Dist: pytest-django ; extra == 'tests'
Requires-Dist: tox ; extra == 'tests'
Requires-Dist: isort ; extra == 'tests'
Requires-Dist: black ; extra == 'tests'
